Transprot/Transprot.py
Transprot/__init__.py
Transprot-1.0.0.2.dist-info/METADATA
Transprot-1.0.0.2.dist-info/WHEEL
Transprot-1.0.0.2.dist-info/top_level.txt
Transprot-1.0.0.2.dist-info/RECORD
